README.md
setup.cfg
setup.py
bagitup/__init__.py
bagitup.egg-info/PKG-INFO
bagitup.egg-info/SOURCES.txt
bagitup.egg-info/dependency_links.txt
bagitup.egg-info/requires.txt
bagitup.egg-info/top_level.txt