Metadata-Version: 2.1
Name: bagitup
Version: 0.0.3
Summary: bagitup is a Pythob based module that enables you to automatically backup your files and databases to Git
Home-page: https://github.com/geetanshjindal/bagitup
Author: Geetansh Jindal
Author-email: geetansh@hackreports.com
License: UNKNOWN
Platform: UNKNOWN
Classifier: Programming Language :: Python :: 3
Classifier: License :: OSI Approved :: MIT License
Classifier: Operating System :: OS Independent
